baidusearch/__init__.py
baidusearch/baidusearch.py
baidusearch-1.0.1.dist-info/LICENSE
baidusearch-1.0.1.dist-info/METADATA
baidusearch-1.0.1.dist-info/WHEEL
baidusearch-1.0.1.dist-info/entry_points.txt
baidusearch-1.0.1.dist-info/top_level.txt
baidusearch-1.0.1.dist-info/RECORD
