Metadata-Version: 2.1
Name: baidusearch
Version: 1.0.1
Summary: Baidu Search unofficial API for Python with no external dependencies
Home-page: https://github.com/wcadaydayup/python-baidusearch
Author: Wu Charles
Author-email: wcadaydayup@163.com
Maintainer: Wu Charles
License: UNKNOWN
Keywords: search-api baidu python
Platform: all
Classifier: Development Status :: 5 - Production/Stable
Classifier: Topic :: Utilities
Classifier: License :: OSI Approved :: MIT License
Classifier: Programming Language :: Python :: 2
Classifier: Programming Language :: Python :: 3
